README.txt
setup.py
src/rbtree.pyx
src/rbtree_impl.c
src/rbtree.egg-info/PKG-INFO
src/rbtree.egg-info/SOURCES.txt
src/rbtree.egg-info/dependency_links.txt
src/rbtree.egg-info/not-zip-safe
src/rbtree.egg-info/top_level.txt