Metadata-Version: 1.0
Name: rbtree
Version: 0.8.8
Summary: A red black tree with extended iterator
Home-page: UNKNOWN
Author: Benjamin Saller
Author-email: bcsaller@gmail.com
License: GPL 3
Download-URL: http://bitbucket.org/bcsaller/rbtree/
Keywords: rbtree red-black tree data-structure
Platform: UNKNOWN
